mri_swarm/__init__.py
mri_swarm/main.py
mri_swarm/prompts.py
mri_swarm-0.1.0.dist-info/LICENSE
mri_swarm-0.1.0.dist-info/METADATA
mri_swarm-0.1.0.dist-info/WHEEL
mri_swarm-0.1.0.dist-info/RECORD
