Metadata-Version: 2.3
Name: mri-swarm
Version: 0.1.0
Summary: MRI-Swarm - TGSC
License: MIT
Keywords: artificial intelligence,deep learning,optimizers,Prompt Engineering,swarms,agents,llms,transformers,multi-agent,swarms of agents,Enterprise-Grade Agents,Production-Grade Agents,Agents,Multi-Grade-Agents,Swarms,Transformers,LLMs,Prompt Engineering,Agents,Generative Agents,Generative AI,Agent Marketplace,Agent Store,quant,finance,algorithmic trading,portfolio optimization,risk management,financial modeling,machine learning for finance,natural language processing for finance,mri,medical i
Author: Kye Gomez
Author-email: kye@apac.ai
Requires-Python: >=3.10,<4.0
Classifier: Development Status :: 4 - Beta
Classifier: Intended Audience :: Developers
Classifier: License :: OSI Approved :: MIT License
Classifier: Programming Language :: Python :: 3
Classifier: Programming Language :: Python :: 3.10
Classifier: Programming Language :: Python :: 3.11
Classifier: Programming Language :: Python :: 3.12
Classifier: Programming Language :: Python :: 3.13
Classifier: Topic :: Scientific/Engineering :: Artificial Intelligence
Requires-Dist: loguru
Requires-Dist: swarms
Project-URL: Documentation, https://docs.swarms.world
Project-URL: Homepage, https://github.com/The-Swarm-Corporation/MRI-Swarm
Project-URL: Repository, https://github.com/The-Swarm-Corporation/MRI-Swarm
